{
  "ComponentIndexes": {},
  "ControlUniqueGuids": {},
  "ControlUniqueIds": {
    "AddMediaButton1": 41,
    "AddMediaWithImage1": 42,
    "App": 1,
    "back": 22,
    "back_1": 11,
    "BarcodeScanner1": 25,
    "btn_saveDB": 19,
    "btn_submit": 32,
    "clear_coll": 7,
    "current_mtr": 27,
    "date_mtr": 29,
    "DateScreenInput": 34,
    "dtp_dateInput": 38,
    "Gallery1": 12,
    "galleryTemplate1": 13,
    "Home": 4,
    "Host": 3,
    "Icon1_1": 36,
    "Image1": 14,
    "Label1": 37,
    "Label2": 23,
    "Label3": 26,
    "Label4": 28,
    "list_mtr_dayli": 9,
    "Logo": 5,
    "mtr_ID": 24,
    "mtrScreenInput": 20,
    "NextArrow1": 16,
    "Rectangle1": 35,
    "Rectangle1_1": 21,
    "Rectangle1_2": 10,
    "saveDate": 39,
    "Separator1": 18,
    "start_input": 6,
    "Subtitle1": 17,
    "Title1": 15,
    "UploadedImage1": 40,
    "view_call": 8
  },
  "FunctionParamsInvariantScripts": {},
  "FunctionParamsInvariantScriptsOnInstances": {},
  "HeaderLastSavedDateTimeUTC": "06/28/2023 06:12:08",
  "IsLegacyComponentAllowGlobalScopeCase": false,
  "LocalConnectionIDReferences": {
    "88f67e0e-d717-4813-aa7f-5f18c45ef801": "\"/providers/microsoft.powerapps/apis/shared_logicflows/connections/0e7b49813a7c4510b46cf9828baed0c8-3d4fb6fe7b9c0641\"",
    "e3800f7b-2050-4a3f-9b67-987d6951004a": "\"/providers/microsoft.powerapps/apis/shared_sharepointonline/connections/a406262431d04a618364042ad20a1b96\""
  },
  "LocalDatabaseReferencesAsEmpty": false,
  "LocalResourceFileNames": {
    "scs logo": "0001.png"
  },
  "LocalResourceRootPaths": {
    "scs logo": "https://docserverpwaprodseas.blob.core.windows.net/d31cb686-0f9a-4f4d-8c60-5b54f37f6001-1/resource/Assets0Images00001.png?sv=2018-03-28&sr=b&sig=T72gE4zZjteRAXohB%2FLDucwyHY5cQlnE4JE1B2MkyVc%3D&spr=https&se=2023-06-29T06%3A24%3A31Z&sp=r"
  },
  "OrderComponentMetadata": {},
  "OrderComponentTemplate": {},
  "OrderDataSource": {
    "[DEV]-UploadImageWaterMeter": 0,
    "CustomGallerySample": 1,
    "tbl_metering_logs": 2
  },
  "OrderGroupControls": {
    "AddMediaWithImage1": {
      "AddMediaButton1": 1,
      "UploadedImage1": 0
    }
  },
  "OrderPcfTemplate": {},
  "OrderTemplate": {},
  "OrderXMLTemplate": {
    "addMedia": 6,
    "barcodeScanner": 8,
    "button": 1,
    "datepicker": 9,
    "gallery": 4,
    "icon": 3,
    "image": 0,
    "label": 5,
    "rectangle": 2,
    "text": 7
  },
  "OverridablePropertiesEntry": {
    "AddMediaButton1": {},
    "AddMediaWithImage1": {},
    "App": {},
    "back": {},
    "back_1": {},
    "BarcodeScanner1": {},
    "btn_saveDB": {},
    "btn_submit": {},
    "clear_coll": {},
    "current_mtr": {},
    "date_mtr": {},
    "DateScreenInput": {},
    "dtp_dateInput": {},
    "Gallery1": {},
    "galleryTemplate1": {},
    "Home": {},
    "Host": {},
    "Icon1_1": {},
    "Image1": {},
    "Label1": {},
    "Label2": {},
    "Label3": {},
    "Label4": {},
    "list_mtr_dayli": {},
    "Logo": {},
    "mtr_ID": {},
    "mtrScreenInput": {},
    "NextArrow1": {},
    "Rectangle1": {},
    "Rectangle1_1": {},
    "Rectangle1_2": {},
    "saveDate": {},
    "Separator1": {},
    "start_input": {},
    "Subtitle1": {},
    "Title1": {},
    "UploadedImage1": {},
    "view_call": {}
  },
  "PCFDynamicSchemaForIRRetrievalEntry": {},
  "PCFTemplateEntry": {},
  "PublishOrderIndices": {
    "AddMediaButton1": 0,
    "AddMediaWithImage1": 0,
    "App": 0,
    "back": 27,
    "back_1": 16,
    "BarcodeScanner1": 30,
    "btn_saveDB": 18,
    "btn_submit": 37,
    "clear_coll": 12,
    "current_mtr": 32,
    "date_mtr": 34,
    "DateScreenInput": 3,
    "dtp_dateInput": 7,
    "Gallery1": 17,
    "galleryTemplate1": 19,
    "Home": 9,
    "Host": 0,
    "Icon1_1": 5,
    "Image1": 20,
    "Label1": 6,
    "Label2": 28,
    "Label3": 31,
    "Label4": 33,
    "list_mtr_dayli": 14,
    "Logo": 10,
    "mtr_ID": 29,
    "mtrScreenInput": 25,
    "NextArrow1": 22,
    "Rectangle1": 4,
    "Rectangle1_1": 26,
    "Rectangle1_2": 15,
    "saveDate": 8,
    "Separator1": 24,
    "start_input": 11,
    "Subtitle1": 23,
    "Title1": 21,
    "UploadedImage1": 0,
    "view_call": 13
  },
  "ResourcesJsonIndices": {
    "Image-SampleImage": 0,
    "Image-scs logo": 1
  },
  "RuleScreenIdWithoutScreen": {},
  "TemplateVersions": {},
  "VolatileProperties": {
    "AnalysisLoadTime": 0.2690689,
    "ControlCount": {
      "addMedia": 1,
      "barcodeScanner": 1,
      "button": 6,
      "datepicker": 2,
      "gallery": 1,
      "galleryTemplate": 1,
      "group": 1,
      "icon": 4,
      "image": 3,
      "label": 6,
      "rectangle": 4,
      "screen": 4,
      "text": 2
    },
    "DeserializationLoadTime": 1.0771417
  },
  "WasLocalDatabaseReferencesEmpty": true
}